displayio_listselect.py
circuitpython_displayio_listselect-1.0.2.dist-info/LICENSE
circuitpython_displayio_listselect-1.0.2.dist-info/METADATA
circuitpython_displayio_listselect-1.0.2.dist-info/WHEEL
circuitpython_displayio_listselect-1.0.2.dist-info/top_level.txt
circuitpython_displayio_listselect-1.0.2.dist-info/RECORD
