Metadata-Version: 2.1
Name: circuitpython-displayio-listselect
Version: 1.0.2
Summary: ListSelect widget for circuitpython displayio. Display a list of strings with a selection indicator allow user to move selection up and down.
Author-email: Adafruit Industries <circuitpython@adafruit.com>
License: MIT
Project-URL: Homepage, https://github.com/foamyguy/CircuitPython_DisplayIO_ListSelect
Keywords: adafruit,blinka,circuitpython,micropython,displayio_listselect,list,select,listselect,dropdown,choice,choose,chooser,options,menu
Classifier: Intended Audience :: Developers
Classifier: Topic :: Software Development :: Libraries
Classifier: Topic :: Software Development :: Embedded Systems
Classifier: Topic :: System :: Hardware
Classifier: License :: OSI Approved :: MIT License
Classifier: Programming Language :: Python :: 3
License-File: LICENSE
Requires-Dist: Adafruit-Blinka
Requires-Dist: adafruit-circuitpython-display-text
Provides-Extra: optional
